nodeinfo/__init__.py
nodeinfo/__main__.py
nodeinfo/main.py
pynodeinfo-0.1.2.dist-info/LICENSE
pynodeinfo-0.1.2.dist-info/WHEEL
pynodeinfo-0.1.2.dist-info/METADATA
pynodeinfo-0.1.2.dist-info/RECORD
